dexflex/__init__.py
dexflex/data_loader.py
dexflex/data_worker.py
dexflex/evalLS.py
dexflex/json_creator.py
dexflex/prototype.py
dexflex/util_data.py
dexflex-0.0.9.dist-info/METADATA
dexflex-0.0.9.dist-info/WHEEL
dexflex-0.0.9.dist-info/top_level.txt
dexflex-0.0.9.dist-info/RECORD
