Metadata-Version: 2.1
Name: dexflex
Version: 0.0.9
Summary: Spacy plugin working based on dexonline database
Author: Cristea Petru-Theodor
Author-email: petru.theodor@outlook.com
Requires-Dist: numpy (==1.26.4)
Requires-Dist: requests (==2.31.0)
Requires-Dist: mariadb
Requires-Dist: feather-format
Requires-Dist: zipp (==3.17.0)
Requires-Dist: tqdm (==4.66.1)
Requires-Dist: torch
Requires-Dist: spacy (==3.7.2)
Requires-Dist: transformers (==4.36.2)
Requires-Dist: wordfreq
